gdb_async/__init__.py
gdb_async/main.py
gdb_async-1.0.0.dist-info/METADATA
gdb_async-1.0.0.dist-info/WHEEL
gdb_async-1.0.0.dist-info/top_level.txt
gdb_async-1.0.0.dist-info/RECORD
